XceptHttp/__init__.py
xcepthttp-0.0.2.dist-info/METADATA
xcepthttp-0.0.2.dist-info/WHEEL
xcepthttp-0.0.2.dist-info/licenses/LICENSE
xcepthttp-0.0.2.dist-info/RECORD
