Metadata-Version: 2.4
Name: XceptHttp
Version: 0.0.2
Summary: XceptHttp is a powerful, easy-to-use Python library built on top of httpx to simplify HTTP request handling. With intuitive methods for making asynchronous and synchronous HTTP requests.
Project-URL: Homepage, https://github.com/PyLC/hmPy
Project-URL: Issues, https://github.com/PyLC/hmPy
Author-email: OperatorV <kendricklamar@gmail.com>
License-File: LICENSE
Classifier: License :: OSI Approved :: GNU General Public License v3 (GPLv3)
Classifier: Operating System :: OS Independent
Classifier: Programming Language :: Python :: 3
Requires-Python: >=3.0
